hart_protocol/VERSION
hart_protocol/__init__.py
hart_protocol/__version__.py
hart_protocol/_parsing.py
hart_protocol/_unpacker.py
hart_protocol/common.py
hart_protocol/py.typed
hart_protocol/tools.py
hart_protocol/universal.py
hart_protocol-2023.5.0.dist-info/LICENSE
hart_protocol-2023.5.0.dist-info/WHEEL
hart_protocol-2023.5.0.dist-info/METADATA
hart_protocol-2023.5.0.dist-info/RECORD
