Metadata-Version: 2.1
Name: hart-protocol
Version: 2023.5.0
Summary: A sans-io python implementation of the Highway Addressable Remote Transducer Protocol.
Home-page: https://github.com/yaq-project/hart-protocol
Author: Blaise Thompson
Requires-Python: >=3.7
Classifier: Development Status :: 2 - Pre-Alpha
Classifier: Intended Audience :: Science/Research
Classifier: License :: OSI Approved :: GNU Lesser General Public License v3 (LGPLv3)
Classifier: Natural Language :: English
Classifier: Programming Language :: Python :: 3
Classifier: Programming Language :: Python :: 3.7
Classifier: Programming Language :: Python :: 3.8
Classifier: Programming Language :: Python :: 3.9
Classifier: Programming Language :: Python :: 3.10
Classifier: Topic :: Scientific/Engineering
Requires-Dist: black ; extra == "dev"
Requires-Dist: pre-commit ; extra == "dev"
Project-URL: Issues, https://github.com/yaq-project/hart-protocol/issues
Project-URL: Source, https://github.com/yaq-project/hart-protocol
Provides-Extra: dev
